cmakew/__init__.py
cmakew/__version__.py
cmakew/_cd.py
cmakew/_common.py
cmakew/_compiler.py
cmakew/_logger.py
cmakew/_option.py
cmakew/_visual_studio.py
cmakew/cmakew.py
cmakew-0.2.0.dist-info/LICENSE
cmakew-0.2.0.dist-info/METADATA
cmakew-0.2.0.dist-info/WHEEL
cmakew-0.2.0.dist-info/entry_points.txt
cmakew-0.2.0.dist-info/top_level.txt
cmakew-0.2.0.dist-info/RECORD
