Metadata-Version: 2.1
Name: cmakew
Version: 0.2.0
Summary: cmakew is a CMake wrapper CLI tool.
Home-page: https://github.com/thombashi/cmakew
Author: Tsuyoshi Hombashi
Author-email: tsuyoshi.hombashi@gmail.com
License: MIT License
Project-URL: Source, https://github.com/thombashi/cmakew
Project-URL: Tracker, https://github.com/thombashi/cmakew/issues
Keywords: cmake,build,Visual Studio
Platform: UNKNOWN
Classifier: Development Status :: 4 - Beta
Classifier: Environment :: Console
Classifier: Intended Audience :: Developers
Classifier: Intended Audience :: Information Technology
Classifier: License :: OSI Approved :: MIT License
Classifier: Operating System :: Microsoft :: Windows
Classifier: Operating System :: POSIX
Classifier: Operating System :: POSIX :: Linux
Classifier: Programming Language :: Python :: 2
Classifier: Programming Language :: Python :: 2.7
Classifier: Programming Language :: Python :: 3
Classifier: Programming Language :: Python :: 3.5
Classifier: Programming Language :: Python :: 3.6
Classifier: Programming Language :: Python :: 3.7
Classifier: Topic :: Software Development :: Build Tools
Requires-Python: >=2.7, !=3.0.*, !=3.1.*, !=3.2.*, !=3.3.*, !=3.4.*
Requires-Dist: Logbook (<2.0.0,>=0.12.3)
Requires-Dist: six (<2.0.0,>=1.10.0)
Requires-Dist: subprocrunner (<1.0.0,>=0.17.0)
Requires-Dist: typepy (<1.0.0,>=0.5.0)
Provides-Extra: build
Requires-Dist: twine ; extra == 'build'
Requires-Dist: wheel ; extra == 'build'
Provides-Extra: release
Requires-Dist: releasecmd (<0.1.0,>=0.0.18) ; extra == 'release'
